{ "frames": [ { "filename": "ball_selected", "frame": { "x": 701, "y": 465, "w": 85, "h": 85 }, "rotated": false, "trimmed": false, "spriteSourceSize": { "x": 0, "y": 0, "w": 85, "h": 85 }, "sourceSize": { "w": 85, "h": 85 } }, { "filename": "balls_panel", "frame": { "x": 0, "y": 465, "w": 700, "h": 440 }, "rotated": false, "trimmed": false, "spriteSourceSize": { "x": 0, "y": 0, "w": 700, "h": 440 }, "sourceSize": { "w": 700, "h": 440 } }, { "filename": "button_menu", "frame": { "x": 366, "y": 76, "w": 70, "h": 70 }, "rotated": false, "trimmed": false, "spriteSourceSize": { "x": 0, "y": 0, "w": 70, "h": 70 }, "sourceSize": { "w": 70, "h": 70 } }, { "filename": "button_more_games", "frame": { "x": 808, "y": 602, "w": 70, "h": 70 }, "rotated": false, "trimmed": false, "spriteSourceSize": { "x": 0, "y": 0, "w": 70, "h": 70 }, "sourceSize": { "w": 70, "h": 70 } }, { "filename": "button_ok", "frame": { "x": 808, "y": 749, "w": 100, "h": 100 }, "rotated": false, "trimmed": false, "spriteSourceSize": { "x": 0, "y": 0, "w": 100, "h": 100 }, "sourceSize": { "w": 100, "h": 100 } }, { "filename": "button_pause", "frame": { "x": 301, "y": 331, "w": 60, "h": 60 }, "rotated": false, "trimmed": false, "spriteSourceSize": { "x": 0, "y": 0, "w": 60, "h": 60 }, "sourceSize": { "w": 60, "h": 60 } }, { "filename": "button_restart", "frame": { "x": 808, "y": 0, "w": 110, "h": 110 }, "rotated": false, "trimmed": false, "spriteSourceSize": { "x": 0, "y": 0, "w": 110, "h": 110 }, "sourceSize": { "w": 110, "h": 110 } }, { "filename": "button_resume", "frame": { "x": 808, "y": 111, "w": 110, "h": 110 }, "rotated": false, "trimmed": false, "spriteSourceSize": { "x": 0, "y": 0, "w": 110, "h": 110 }, "sourceSize": { "w": 110, "h": 110 } }, { "filename": "game_end_panel", "frame": { "x": 442, "y": 0, "w": 365, "h": 400 }, "rotated": false, "trimmed": false, "spriteSourceSize": { "x": 0, "y": 0, "w": 365, "h": 400 }, "sourceSize": { "w": 365, "h": 400 } }, { "filename": "menu_ball_1", "frame": { "x": 701, "y": 551, "w": 75, "h": 75 }, "rotated": false, "trimmed": false, "spriteSourceSize": { "x": 0, "y": 0, "w": 75, "h": 75 }, "sourceSize": { "w": 75, "h": 75 } }, { "filename": "menu_ball_10", "frame": { "x": 701, "y": 779, "w": 75, "h": 75 }, "rotated": false, "trimmed": false, "spriteSourceSize": { "x": 0, "y": 0, "w": 75, "h": 75 }, "sourceSize": { "w": 75, "h": 75 } }, { "filename": "menu_ball_11", "frame": { "x": 366, "y": 299, "w": 75, "h": 75 }, "rotated": false, "trimmed": false, "spriteSourceSize": { "x": 0, "y": 0, "w": 75, "h": 75 }, "sourceSize": { "w": 75, "h": 75 } }, { "filename": "menu_ball_12", "frame": { "x": 808, "y": 222, "w": 75, "h": 75 }, "rotated": false, "trimmed": false, "spriteSourceSize": { "x": 0, "y": 0, "w": 75, "h": 75 }, "sourceSize": { "w": 75, "h": 75 } }, { "filename": "menu_ball_13", "frame": { "x": 366, "y": 223, "w": 75, "h": 75 }, "rotated": false, "trimmed": false, "spriteSourceSize": { "x": 0, "y": 0, "w": 75, "h": 75 }, "sourceSize": { "w": 75, "h": 75 } }, { "filename": "menu_ball_14", "frame": { "x": 808, "y": 374, "w": 75, "h": 75 }, "rotated": false, "trimmed": false, "spriteSourceSize": { "x": 0, "y": 0, "w": 75, "h": 75 }, "sourceSize": { "w": 75, "h": 75 } }, { "filename": "menu_ball_15", "frame": { "x": 366, "y": 147, "w": 75, "h": 75 }, "rotated": false, "trimmed": false, "spriteSourceSize": { "x": 0, "y": 0, "w": 75, "h": 75 }, "sourceSize": { "w": 75, "h": 75 } }, { "filename": "menu_ball_2", "frame": { "x": 808, "y": 298, "w": 75, "h": 75 }, "rotated": false, "trimmed": false, "spriteSourceSize": { "x": 0, "y": 0, "w": 75, "h": 75 }, "sourceSize": { "w": 75, "h": 75 } }, { "filename": "menu_ball_3", "frame": { "x": 366, "y": 375, "w": 75, "h": 75 }, "rotated": false, "trimmed": false, "spriteSourceSize": { "x": 0, "y": 0, "w": 75, "h": 75 }, "sourceSize": { "w": 75, "h": 75 } }, { "filename": "menu_ball_4", "frame": { "x": 808, "y": 526, "w": 75, "h": 75 }, "rotated": false, "trimmed": false, "spriteSourceSize": { "x": 0, "y": 0, "w": 75, "h": 75 }, "sourceSize": { "w": 75, "h": 75 } }, { "filename": "menu_ball_5", "frame": { "x": 701, "y": 627, "w": 75, "h": 75 }, "rotated": false, "trimmed": false, "spriteSourceSize": { "x": 0, "y": 0, "w": 75, "h": 75 }, "sourceSize": { "w": 75, "h": 75 } }, { "filename": "menu_ball_6", "frame": { "x": 366, "y": 0, "w": 75, "h": 75 }, "rotated": false, "trimmed": false, "spriteSourceSize": { "x": 0, "y": 0, "w": 75, "h": 75 }, "sourceSize": { "w": 75, "h": 75 } }, { "filename": "menu_ball_7", "frame": { "x": 701, "y": 703, "w": 75, "h": 75 }, "rotated": false, "trimmed": false, "spriteSourceSize": { "x": 0, "y": 0, "w": 75, "h": 75 }, "sourceSize": { "w": 75, "h": 75 } }, { "filename": "menu_ball_8", "frame": { "x": 808, "y": 673, "w": 75, "h": 75 }, "rotated": false, "trimmed": false, "spriteSourceSize": { "x": 0, "y": 0, "w": 75, "h": 75 }, "sourceSize": { "w": 75, "h": 75 } }, { "filename": "menu_ball_9", "frame": { "x": 808, "y": 450, "w": 75, "h": 75 }, "rotated": false, "trimmed": false, "spriteSourceSize": { "x": 0, "y": 0, "w": 75, "h": 75 }, "sourceSize": { "w": 75, "h": 75 } }, { "filename": "overlay_bg", "frame": { "x": 702, "y": 856, "w": 48, "h": 48 }, "rotated": false, "trimmed": false, "spriteSourceSize": { "x": 0, "y": 0, "w": 50, "h": 50 }, "sourceSize": { "w": 50, "h": 50 } }, { "filename": "pause_branding", "frame": { "x": 0, "y": 331, "w": 300, "h": 80 }, "rotated": false, "trimmed": false, "spriteSourceSize": { "x": 0, "y": 0, "w": 300, "h": 80 }, "sourceSize": { "w": 300, "h": 80 } }, { "filename": "pause_panel", "frame": { "x": 0, "y": 0, "w": 365, "h": 330 }, "rotated": false, "trimmed": false, "spriteSourceSize": { "x": 0, "y": 0, "w": 365, "h": 330 }, "sourceSize": { "w": 365, "h": 330 } }, { "filename": "store_download", "frame": { "x": 442, "y": 401, "w": 160, "h": 52 }, "rotated": false, "trimmed": false, "spriteSourceSize": { "x": 0, "y": 0, "w": 160, "h": 52 }, "sourceSize": { "w": 160, "h": 52 } }, { "filename": "store_google", "frame": { "x": 603, "y": 401, "w": 160, "h": 52 }, "rotated": false, "trimmed": false, "spriteSourceSize": { "x": 0, "y": 0, "w": 160, "h": 52 }, "sourceSize": { "w": 160, "h": 52 } }, { "filename": "store_ios", "frame": { "x": 161, "y": 412, "w": 160, "h": 52 }, "rotated": false, "trimmed": false, "spriteSourceSize": { "x": 0, "y": 0, "w": 160, "h": 52 }, "sourceSize": { "w": 160, "h": 52 } }, { "filename": "store_winphone", "frame": { "x": 0, "y": 412, "w": 160, "h": 52 }, "rotated": false, "trimmed": false, "spriteSourceSize": { "x": 0, "y": 0, "w": 160, "h": 52 }, "sourceSize": { "w": 160, "h": 52 } } ], "meta": { "app": "http://www.leshylabs.com/apps/sstool/", "version": "Leshy SpriteSheet Tool v0.8.1", "size": { "w": 918, "h": 905 }, "scale": 1 } }